gptwc/__init__.py
gptwc/gptwc.py
gptwc-1.3.0.dist-info/LICENSE
gptwc-1.3.0.dist-info/METADATA
gptwc-1.3.0.dist-info/WHEEL
gptwc-1.3.0.dist-info/entry_points.txt
gptwc-1.3.0.dist-info/top_level.txt
gptwc-1.3.0.dist-info/RECORD
