Metadata-Version: 2.1
Name: gptwc
Version: 1.3.0
Summary: A package to count tokens in input text using OpenAI's tiktoken library.
Home-page: https://github.com/lwneal/gptwc
Author: Lawrence Neal
Author-email: nealla@lwneal.com
License: UNKNOWN
Platform: UNKNOWN
Requires-Python: >=3.6
License-File: LICENSE
Requires-Dist: pyperclip
Requires-Dist: tiktoken >=0.7.0
